setup.py
django_qrmixin.egg-info/PKG-INFO
django_qrmixin.egg-info/SOURCES.txt
django_qrmixin.egg-info/dependency_links.txt
django_qrmixin.egg-info/requires.txt
django_qrmixin.egg-info/top_level.txt
qrmixin/__init__.py