Metadata-Version: 1.0
Name: django-qrmixin
Version: 1.0.1
Summary: Provides a QR code generating mixin for django models
Home-page: https://bitbucket.org/freakypie/django-qrmixin
Author: Danemco, LLC
Author-email: dev@velocitywebworks.com
License: UNKNOWN
Platform: UNKNOWN
